matrix/__init__.py
matrix/elementary.py
difftest-0.1.1.dist-info/METADATA
difftest-0.1.1.dist-info/WHEEL
difftest-0.1.1.dist-info/top_level.txt
difftest-0.1.1.dist-info/RECORD
