Metadata-Version: 2.4
Name: difftest
Version: 0.1.1
Summary: Your project description
Author: Fereshteh Molaverdi
License-Expression: MIT
Project-URL: Homepage, https://github.com/neonunicorngh/difftest
Classifier: Programming Language :: Python :: 3
Classifier: Operating System :: OS Independent
Requires-Python: >=3.12
Requires-Dist: matplotlib>=3.10.6
Requires-Dist: torch>=2.8.0
Requires-Dist: neonunicorn>=0.1.0
Provides-Extra: dev
Requires-Dist: ipykernel>=6.30.1; extra == "dev"
Requires-Dist: jupyter>=1.1.1; extra == "dev"
